<?xml version="1.0" encoding="UTF-8"?>
<con:soapui-project id="cffb0199-39ee-415b-ab78-32426d110c76" activeEnvironment="Default" name="Kodilla Courses" soapui-version="5.7.0" abortOnError="false" runType="SEQUENTIAL" xmlns:con="http://eviware.com/soapui/config"><con:settings/><con:interface xsi:type="con:WsdlInterface" id="42a6c6a5-3d71-4889-a768-e7f1e5d32496" wsaVersion="NONE" name="CoursesPortSoap11" type="wsdl" bindingName="{http://kodilla.com/courses/soap}CoursesPortSoap11" soapVersion="1_1" anonymous="optional" definition="http://localhost:8080/ws/courses.wsdl" xmlns:xsi="http://www.w3.org/2001/XMLSchema-instance"><con:settings/><con:definitionCache type="TEXT" rootPart="http://localhost:8080/ws/courses.wsdl"><con:part><con:url>http://localhost:8080/ws/courses.wsdl</con:url><con:content><![CDATA[<wsdl:definitions targetNamespace="http://kodilla.com/courses/soap" xmlns:wsdl="http://schemas.xmlsoap.org/wsdl/" xmlns:sch="http://kodilla.com/courses/soap" xmlns:soap="http://schemas.xmlsoap.org/wsdl/soap/" xmlns:tns="http://kodilla.com/courses/soap">
  <wsdl:types>
    <xs:schema elementFormDefault="qualified" targetNamespace="http://kodilla.com/courses/soap" xmlns:xs="http://www.w3.org/2001/XMLSchema">
      <xs:element name="getCourseRequest">
        <xs:complexType>
          <xs:sequence>
            <xs:element name="name" type="xs:string"/>
          </xs:sequence>
        </xs:complexType>
      </xs:element>
      <xs:element name="getCourseResponse">
        <xs:complexType>
          <xs:sequence>
            <xs:element name="course" type="tns:course"/>
          </xs:sequence>
        </xs:complexType>
      </xs:element>
      <xs:complexType name="course">
        <xs:sequence>
          <xs:element name="name" type="xs:string"/>
          <xs:element name="length" type="xs:int"/>
          <xs:element name="technology" type="tns:technology"/>
        </xs:sequence>
      </xs:complexType>
      <xs:simpleType name="technology">
        <xs:restriction base="xs:string">
          <xs:enumeration value="JAVA"/>
          <xs:enumeration value="JAVASCRIPT"/>
          <xs:enumeration value="HTML"/>
        </xs:restriction>
      </xs:simpleType>
    </xs:schema>
  </wsdl:types>
  <wsdl:message name="getCourseResponse">
    <wsdl:part element="tns:getCourseResponse" name="getCourseResponse"></wsdl:part>
  </wsdl:message>
  <wsdl:message name="getCourseRequest">
    <wsdl:part element="tns:getCourseRequest" name="getCourseRequest"></wsdl:part>
  </wsdl:message>
  <wsdl:portType name="CoursesPort">
    <wsdl:operation name="getCourse">
      <wsdl:input message="tns:getCourseRequest" name="getCourseRequest"></wsdl:input>
      <wsdl:output message="tns:getCourseResponse" name="getCourseResponse"></wsdl:output>
    </wsdl:operation>
  </wsdl:portType>
  <wsdl:binding name="CoursesPortSoap11" type="tns:CoursesPort">
    <soap:binding style="document" transport="http://schemas.xmlsoap.org/soap/http"/>
    <wsdl:operation name="getCourse">
      <soap:operation soapAction=""/>
      <wsdl:input name="getCourseRequest">
        <soap:body use="literal"/>
      </wsdl:input>
      <wsdl:output name="getCourseResponse">
        <soap:body use="literal"/>
      </wsdl:output>
    </wsdl:operation>
  </wsdl:binding>
  <wsdl:service name="CoursesPortService">
    <wsdl:port binding="tns:CoursesPortSoap11" name="CoursesPortSoap11">
      <soap:address location="http://localhost:8080/ws"/>
    </wsdl:port>
  </wsdl:service>
</wsdl:definitions>]]></con:content><con:type>http://schemas.xmlsoap.org/wsdl/</con:type></con:part></con:definitionCache><con:endpoints><con:endpoint>http://localhost:8080/ws</con:endpoint></con:endpoints><con:operation id="48a2385d-a960-4e68-ba50-daf640d47e03" isOneWay="false" action="" name="getCourse" bindingOperationName="getCourse" type="Request-Response" outputName="getCourseResponse" inputName="getCourseRequest" receivesAttachments="false" sendsAttachments="false" anonymous="optional"><con:settings/><con:call id="50143f0a-fdf4-4cf7-bdc3-a115968860fa" name="Request 1"><con:settings><con:setting id="com.eviware.soapui.impl.wsdl.WsdlRequest@request-headers">&lt;xml-fragment/></con:setting></con:settings><con:encoding>UTF-8</con:encoding><con:endpoint>http://localhost:8080/ws</con:endpoint><con:request><![CDATA[<soapenv:Envelope xmlns:soapenv="http://schemas.xmlsoap.org/soap/envelope/" xmlns:soap="http://kodilla.com/courses/soap">\r
   <soapenv:Header/>\r
   <soapenv:Body>\r
      <soap:getCourseRequest>\r
         <soap:name>Java Developer</soap:name>\r
      </soap:getCourseRequest>\r
   </soapenv:Body>\r
</soapenv:Envelope>]]></con:request><con:credentials><con:authType>No Authorization</con:authType></con:credentials><con:jmsConfig JMSDeliveryMode="PERSISTENT"/><con:jmsPropertyConfig/><con:wsaConfig mustUnderstand="NONE" version="200508" action="http://kodilla.com/courses/soap/CoursesPort/getCourseRequest"/><con:wsrmConfig version="1.2"/></con:call></con:operation></con:interface><con:testSuite id="3ca76405-d238-4f90-b2e6-4b74dff69cb4" name="Kodilla Courses TestSuite"><con:settings/><con:runType>SEQUENTIAL</con:runType><con:testCase id="ade2c7e1-0ff7-4c75-9aaa-ab9eb0c318ff" failOnError="true" failTestCaseOnErrors="true" keepSession="false" maxResults="0" name="Not existing course TestCase" searchProperties="true"><con:settings/><con:testStep type="request" id="10bbb60f-f0ac-4264-b7ba-c3bc370ccea8" name="getCourse"><con:settings/><con:config xsi:type="con:RequestStep" xmlns:xsi="http://www.w3.org/2001/XMLSchema-instance"><con:interface>CoursesPortSoap11</con:interface><con:operation>getCourse</con:operation><con:request name="getCourse" id="ed76a055-98c1-4cc8-a00f-5988cf354756"><con:settings><con:setting id="com.eviware.soapui.impl.wsdl.WsdlRequest@request-headers">&lt;xml-fragment/></con:setting></con:settings><con:encoding>UTF-8</con:encoding><con:endpoint>http://localhost:8080/ws</con:endpoint><con:request><![CDATA[<soapenv:Envelope xmlns:soapenv="http://schemas.xmlsoap.org/soap/envelope/" xmlns:soap="http://kodilla.com/courses/soap">\r
   <soapenv:Header/>\r
   <soapenv:Body>\r
      <soap:getCourseRequest>\r
         <soap:name>Java Developer Plus </soap:name>\r
      </soap:getCourseRequest>\r
   </soapenv:Body>\r
</soapenv:Envelope>]]></con:request><con:assertion type="Simple NotContains" id="df12f08c-a7ac-444f-9fb0-a6396844868d" name="Not Contains"><con:configuration><token>length</token><ignoreCase>false</ignoreCase><useRegEx>false</useRegEx></con:configuration></con:assertion><con:credentials><con:authType>No Authorization</con:authType></con:credentials><con:jmsConfig JMSDeliveryMode="PERSISTENT"/><con:jmsPropertyConfig/><con:wsaConfig action="http://kodilla.com/courses/soap/CoursesPort/getCourseRequest" mustUnderstand="NONE" version="200508"/><con:wsrmConfig version="1.2"/></con:request></con:config></con:testStep><con:properties/></con:testCase><con:testCase id="91a697d8-4610-4617-bfad-44032204955a" failOnError="true" failTestCaseOnErrors="true" keepSession="false" maxResults="0" name="Course 9 months length TestCase" searchProperties="true"><con:settings/><con:testStep type="request" id="fc801155-8a0b-4347-8719-291b5b05a39f" name="getCourse"><con:settings/><con:config xsi:type="con:RequestStep" xmlns:xsi="http://www.w3.org/2001/XMLSchema-instance"><con:interface>CoursesPortSoap11</con:interface><con:operation>getCourse</con:operation><con:request name="getCourse" id="ed76a055-98c1-4cc8-a00f-5988cf354756"><con:settings><con:setting id="com.eviware.soapui.impl.wsdl.WsdlRequest@request-headers">&lt;xml-fragment/></con:setting></con:settings><con:encoding>UTF-8</con:encoding><con:endpoint>http://localhost:8080/ws</con:endpoint><con:request><![CDATA[<soapenv:Envelope xmlns:soapenv="http://schemas.xmlsoap.org/soap/envelope/" xmlns:soap="http://kodilla.com/courses/soap">\r
   <soapenv:Header/>\r
   <soapenv:Body>\r
      <soap:getCourseRequest>\r
         <soap:name>Java Developer</soap:name>\r
      </soap:getCourseRequest>\r
   </soapenv:Body>\r
</soapenv:Envelope>]]></con:request><con:assertion type="Simple Contains" id="e9d267f2-4638-4fa9-a0cc-c387808290e7" name="Contains"><con:configuration><token>length>6&lt;</token><ignoreCase>false</ignoreCase><useRegEx>false</useRegEx></con:configuration></con:assertion><con:credentials><con:authType>No Authorization</con:authType></con:credentials><con:jmsConfig JMSDeliveryMode="PERSISTENT"/><con:jmsPropertyConfig/><con:wsaConfig action="http://kodilla.com/courses/soap/CoursesPort/getCourseRequest" mustUnderstand="NONE" version="200508"/><con:wsrmConfig version="1.2"/></con:request></con:config></con:testStep><con:properties/></con:testCase><con:testCase id="608c7896-b18a-46de-b33b-875d17d10be2" failOnError="true" failTestCaseOnErrors="true" keepSession="false" maxResults="0" name="Course 6 months length TestCase" searchProperties="true"><con:settings/><con:testStep type="request" id="d6529bc0-ee68-4202-82f0-3c5f3f7b1f8f" name="getCourse"><con:settings/><con:config xsi:type="con:RequestStep" xmlns:xsi="http://www.w3.org/2001/XMLSchema-instance"><con:interface>CoursesPortSoap11</con:interface><con:operation>getCourse</con:operation><con:request name="getCourse" id="ed76a055-98c1-4cc8-a00f-5988cf354756"><con:settings><con:setting id="com.eviware.soapui.impl.wsdl.WsdlRequest@request-headers">&lt;xml-fragment/></con:setting></con:settings><con:encoding>UTF-8</con:encoding><con:endpoint>http://localhost:8080/ws</con:endpoint><con:request><![CDATA[<soapenv:Envelope xmlns:soapenv="http://schemas.xmlsoap.org/soap/envelope/" xmlns:soap="http://kodilla.com/courses/soap">\r
   <soapenv:Header/>\r
   <soapenv:Body>\r
      <soap:getCourseRequest>\r
         <soap:name>Java Developer Plus</soap:name>\r
      </soap:getCourseRequest>\r
   </soapenv:Body>\r
</soapenv:Envelope>]]></con:request><con:assertion type="Simple Contains" id="e9d267f2-4638-4fa9-a0cc-c387808290e7" name="Contains"><con:configuration><token>length>9&lt;</token><ignoreCase>false</ignoreCase><useRegEx>false</useRegEx></con:configuration></con:assertion><con:credentials><con:authType>No Authorization</con:authType></con:credentials><con:jmsConfig JMSDeliveryMode="PERSISTENT"/><con:jmsPropertyConfig/><con:wsaConfig action="http://kodilla.com/courses/soap/CoursesPort/getCourseRequest" mustUnderstand="NONE" version="200508"/><con:wsrmConfig version="1.2"/></con:request></con:config></con:testStep><con:properties/></con:testCase><con:properties/></con:testSuite><con:properties/><con:wssContainer/><con:oAuth2ProfileContainer/><con:oAuth1ProfileContainer/><con:sensitiveInformation/></con:soapui-project>